pyrenren.py
setup.py
pyrenren.egg-info/PKG-INFO
pyrenren.egg-info/SOURCES.txt
pyrenren.egg-info/dependency_links.txt
pyrenren.egg-info/not-zip-safe
pyrenren.egg-info/pbr.json
pyrenren.egg-info/requires.txt
pyrenren.egg-info/top_level.txt