Metadata-Version: 1.0
Name: pyrenren
Version: 1.2
Summary: Python RenRen Client
Home-page: https://github.com/wong2/pyrenren
Author: wong2
Author-email: wonderfuly@gmail.com
License: MIT
Platform: any
